MANIFEST.in
README.md
requirements.txt
setup.cfg
setup.py
opps/__init__.py
opps/ganalytics/__init__.py
opps/ganalytics/admin.py
opps/ganalytics/conf.py
opps/ganalytics/models.py
opps/ganalytics/tasks.py
opps/ganalytics/migrations/0001_initial.py
opps/ganalytics/migrations/0002_auto.py
opps/ganalytics/migrations/__init__.py
opps/ganalytics/templatetags/__init__.py
opps/ganalytics/templatetags/ganalytics_tags.py
opps/ganalytics/utils/__init__.py
opps/ganalytics/utils/create_queries_for_channels.py
opps_ganalytics.egg-info/PKG-INFO
opps_ganalytics.egg-info/SOURCES.txt
opps_ganalytics.egg-info/dependency_links.txt
opps_ganalytics.egg-info/namespace_packages.txt
opps_ganalytics.egg-info/requires.txt
opps_ganalytics.egg-info/top_level.txt