Metadata-Version: 2.1
Name: opps-ganalytics
Version: 0.2.8
Summary: Google Analytics for Opps CMS
Home-page: UNKNOWN
Author: Thiago Avelino
Author-email: avelinorun@gmail.com
License: UNKNOWN
Keywords: google analytics top read
Platform: UNKNOWN
Classifier: Development Status :: 4 - Beta
Classifier: Intended Audience :: Developers
Classifier: Operating System :: OS Independent
Classifier: Framework :: Django
Classifier: Programming Language :: Python
Classifier: Programming Language :: Python :: 2.7
Classifier: Operating System :: OS Independent
Classifier: Topic :: Internet :: WWW/HTTP :: Dynamic Content
Classifier: Topic :: Software Development :: Libraries :: Python Modules
